LICENSE
MANIFEST.in
README.md
gdal2mbt.py
gdal2mbt_cli.py
setup.cfg
setup.py
gdal2mbt.egg-info/PKG-INFO
gdal2mbt.egg-info/SOURCES.txt
gdal2mbt.egg-info/dependency_links.txt
gdal2mbt.egg-info/entry_points.txt
gdal2mbt.egg-info/requires.txt
gdal2mbt.egg-info/top_level.txt