Metadata-Version: 1.1
Name: gdal2mbt
Version: 0.4.1
Summary: Create MBTiles from GDAL files.
Home-page: http://github.com/icetan/gdal2mbt/
Author: Chirstopher Fredén
Author-email: c.freden@gmail.com
License: MIT
Keywords: gdal,mbtiles,gis,tms
Platform: UNKNOWN
Classifier: Development Status :: 4 - Beta
Classifier: Intended Audience :: Developers
Classifier: Natural Language :: English
Classifier: License :: OSI Approved :: MIT License
Classifier: Operating System :: OS Independent
Classifier: Programming Language :: Python
Classifier: Programming Language :: Python :: 2
Classifier: Programming Language :: Python :: 2.6
Classifier: Programming Language :: Python :: 2.7
Classifier: Topic :: Scientific/Engineering :: GIS
